statbat_utils/__init__.py
statbat_utils/general_utils.py
statbat_utils-0.1.0.dist-info/METADATA
statbat_utils-0.1.0.dist-info/WHEEL
statbat_utils-0.1.0.dist-info/RECORD
