Metadata-Version: 2.4
Name: statbat-utils
Version: 0.1.0
Summary: Utility module for StatBat
Author: Chris Peterson
Author-email: chris.will.peterson@gmail.com
Requires-Python: >=3.10
Classifier: Programming Language :: Python :: 3
Classifier: Programming Language :: Python :: 3.10
Classifier: Programming Language :: Python :: 3.11
Classifier: Programming Language :: Python :: 3.12
Classifier: Programming Language :: Python :: 3.13
Classifier: Programming Language :: Python :: 3.14
Requires-Dist: requests (>=2.32.5,<3.0.0)
Requires-Dist: unidecode (>=1.4.0,<2.0.0)
